noop.cp311-win_amd64.pyd
sqlite_robotstxt/__init__.py
sqlite_robotstxt/robotstxt0.dll
sqlite_robotstxt/version.py
sqlite_robotstxt-0.0.1a3.dist-info/METADATA
sqlite_robotstxt-0.0.1a3.dist-info/WHEEL
sqlite_robotstxt-0.0.1a3.dist-info/top_level.txt
sqlite_robotstxt-0.0.1a3.dist-info/RECORD
